setuptricks/__init__.py
setuptricks-0.0.1a2.dist-info/DESCRIPTION.rst
setuptricks-0.0.1a2.dist-info/METADATA
setuptricks-0.0.1a2.dist-info/metadata.json
setuptricks-0.0.1a2.dist-info/RECORD
setuptricks-0.0.1a2.dist-info/top_level.txt
setuptricks-0.0.1a2.dist-info/WHEEL
